mycroft_stt_plugin_elhuyar/__init__.py
mycroft_stt_plugin_elhuyar-1.0.dist-info/DESCRIPTION.rst
mycroft_stt_plugin_elhuyar-1.0.dist-info/METADATA
mycroft_stt_plugin_elhuyar-1.0.dist-info/RECORD
mycroft_stt_plugin_elhuyar-1.0.dist-info/WHEEL
mycroft_stt_plugin_elhuyar-1.0.dist-info/entry_points.txt
mycroft_stt_plugin_elhuyar-1.0.dist-info/metadata.json
mycroft_stt_plugin_elhuyar-1.0.dist-info/top_level.txt
mycroft_stt_plugin_elhuyar-1.0.dist-info/zip-safe
